video_draft_creator/__init__.py
video_draft_creator/__main__.py
video_draft_creator/cli.py
video_draft_creator/config.py
video_draft_creator/config_manager.py
video_draft_creator/corrector.py
video_draft_creator/downloader.py
video_draft_creator/output_formatter.py
video_draft_creator/progress.py
video_draft_creator/transcriber.py
video_draft_creator-0.1.0.dist-info/licenses/LICENSE
video_draft_creator-0.1.0.dist-info/METADATA
video_draft_creator-0.1.0.dist-info/WHEEL
video_draft_creator-0.1.0.dist-info/entry_points.txt
video_draft_creator-0.1.0.dist-info/top_level.txt
video_draft_creator-0.1.0.dist-info/RECORD
