Metadata-Version: 2.4
Name: video-draft-creator
Version: 0.1.0
Summary: 强大的视频音频下载、转录和AI纠错工具
Home-page: https://github.com/yourusername/video-draft-creator
Author: Video Draft Creator Team
Author-email: Video Draft Creator Team <video-draft-creator@example.com>
Maintainer: Video Draft Creator Team
Maintainer-email: Video Draft Creator Team <video-draft-creator@example.com>
License: MIT
Project-URL: Homepage, https://github.com/yourusername/video-draft-creator
Project-URL: Documentation, https://video-draft-creator.readthedocs.io/
Project-URL: Repository, https://github.com/yourusername/video-draft-creator
Project-URL: Bug Reports, https://github.com/yourusername/video-draft-creator/issues
Project-URL: Changelog, https://github.com/yourusername/video-draft-creator/blob/main/CHANGELOG.md
Keywords: video,audio,transcription,whisper,deepseek,download,yt-dlp,speech-to-text,ai,nlp
Platform: any
Classifier: Development Status :: 4 - Beta
Classifier: Intended Audience :: Developers
Classifier: Intended Audience :: End Users/Desktop
Classifier: License :: OSI Approved :: MIT License
Classifier: Operating System :: OS Independent
Classifier: Programming Language :: Python :: 3
Classifier: Programming Language :: Python :: 3.8
Classifier: Programming Language :: Python :: 3.9
Classifier: Programming Language :: Python :: 3.10
Classifier: Programming Language :: Python :: 3.11
Classifier: Programming Language :: Python :: 3.12
Classifier: Topic :: Multimedia :: Video
Classifier: Topic :: Multimedia :: Sound/Audio :: Speech
Requires-Python: >=3.8
License-File: LICENSE
Requires-Dist: yt-dlp>=2024.7.25
Requires-Dist: faster-whisper>=1.0.0
Requires-Dist: requests>=2.32.3
Requires-Dist: Click>=8.1.7
Requires-Dist: python-docx>=1.1.2
Requires-Dist: markdown>=3.6
Requires-Dist: PyYAML>=6.0.1
Provides-Extra: dev
Requires-Dist: pytest>=7.4.4; extra == "dev"
Requires-Dist: pytest-cov>=4.1.0; extra == "dev"
Requires-Dist: pytest-mock>=3.12.0; extra == "dev"
Requires-Dist: pytest-asyncio>=0.23.2; extra == "dev"
Requires-Dist: black>=23.0.0; extra == "dev"
Requires-Dist: isort>=5.12.0; extra == "dev"
Requires-Dist: flake8>=6.0.0; extra == "dev"
Requires-Dist: mypy>=1.0.0; extra == "dev"
Requires-Dist: pre-commit>=3.0.0; extra == "dev"
Provides-Extra: docs
Requires-Dist: sphinx>=7.1.2; extra == "docs"
Requires-Dist: sphinx-rtd-theme>=1.3.0; extra == "docs"
Requires-Dist: sphinx-autodoc-typehints>=1.24.0; extra == "docs"
Requires-Dist: myst-parser>=2.0.0; extra == "docs"
Requires-Dist: sphinx-autobuild>=2021.3.14; extra == "docs"
Provides-Extra: test
Requires-Dist: pytest>=7.4.4; extra == "test"
Requires-Dist: pytest-cov>=4.1.0; extra == "test"
Requires-Dist: pytest-mock>=3.12.0; extra == "test"
Requires-Dist: pytest-asyncio>=0.23.2; extra == "test"
Provides-Extra: gpu
Requires-Dist: torch>=2.0.0; extra == "gpu"
Requires-Dist: torchaudio>=2.0.0; extra == "gpu"
Dynamic: author
Dynamic: home-page
Dynamic: license-file
Dynamic: maintainer
Dynamic: platform
Dynamic: requires-python
